nonebot_plugin_groupmanager/__init__.py
nonebot_plugin_groupmanager/approve.py
nonebot_plugin_groupmanager/config.py
nonebot_plugin_groupmanager/func_hook.py
nonebot_plugin_groupmanager/group_msg.py
nonebot_plugin_groupmanager/group_request_verify.py
nonebot_plugin_groupmanager/img_check.py
nonebot_plugin_groupmanager/notice.py
nonebot_plugin_groupmanager/path.py
nonebot_plugin_groupmanager/request.py
nonebot_plugin_groupmanager/request_manual.py
nonebot_plugin_groupmanager/switcher.py
nonebot_plugin_groupmanager/utils.py
nonebot_plugin_groupmanager/welcome.py
nonebot_plugin_groupmanager/word_analyze.py
nonebot_plugin_groupmanager/wordcloud.py
nonebot_plugin_groupmanager/welcome_utils/__init__.py
nonebot_plugin_groupmanager/welcome_utils/config.py
nonebot_plugin_groupmanager/welcome_utils/message_util.py
nonebot_plugin_groupmanager-1.0.5.dist-info/LICENSE
nonebot_plugin_groupmanager-1.0.5.dist-info/METADATA
nonebot_plugin_groupmanager-1.0.5.dist-info/WHEEL
nonebot_plugin_groupmanager-1.0.5.dist-info/top_level.txt
nonebot_plugin_groupmanager-1.0.5.dist-info/RECORD
