Metadata-Version: 2.1
Name: nonebot-plugin-groupmanager
Version: 1.0.5
Summary: nonebot plugin QQ group manager
Author: HuYihe
Author-email: 2812856215@qq.com
License-File: LICENSE
Requires-Dist: aiofiles
Requires-Dist: fuzzyfinder
Requires-Dist: httpx
Requires-Dist: jieba
Requires-Dist: nonebot-adapter-onebot
Requires-Dist: nonebot2
Requires-Dist: tencentcloud-sdk-python
Requires-Dist: setuptools
Requires-Dist: jinja2
Requires-Dist: pyppeteer
Requires-Dist: imageio
Requires-Dist: numpy
Requires-Dist: nonebot-plugin-apscheduler
Requires-Dist: nonebot-plugin-htmlrender
Requires-Dist: beautifulsoup4
Requires-Dist: lxml
Requires-Dist: Pillow
Requires-Dist: matplotlib
Requires-Dist: xlsxwriter
Requires-Dist: sqlitedict
Requires-Dist: littlepaimon-utils
Requires-Dist: requests
Requires-Dist: pydantic
